MANIFEST.in
README.md
setup.py
so_processing.egg-info/PKG-INFO
so_processing.egg-info/SOURCES.txt
so_processing.egg-info/dependency_links.txt
so_processing.egg-info/not-zip-safe
so_processing.egg-info/requires.txt
so_processing.egg-info/top_level.txt
so_textprocessing/__init__.py
so_textprocessing/data/__init__.py
so_textprocessing/data/sec.txt
so_textprocessing/data/uk_us.csv