Metadata-Version: 1.0
Name: so-processing
Version: 0.2
Summary: SO text processing
Home-page: https://github.cs.adelaide.edu.au/a1720858/so_textprocessing
Author: David Hin
Author-email: a1720858@student.adelaide.edu.au
License: MIT
Platform: UNKNOWN
